{
    "swagger": "2.0",
    "info": {
        "description": "This is a sample server celler server.",
        "title": "Nunu Example API",
        "termsOfService": "http://swagger.io/terms/",
        "contact": {
            "name": "API Support",
            "url": "http://www.swagger.io/support",
            "email": "support@swagger.io"
        },
        "license": {
            "name": "Apache 2.0",
            "url": "http://www.apache.org/licenses/LICENSE-2.0.html"
        },
        "version": "1.0.0"
    },
    "host": "localhost:8000",
    "paths": {
        "/login": {
            "post": {
                "consumes": [
                    "application/json"
                ],
                "produces": [
                    "application/json"
                ],
                "tags": [
                    "用户模块"
                ],
                "summary": "账号登录",
                "parameters": [
                    {
                        "description": "params",
                        "name": "request",
                        "in": "body",
                        "required": true,
                        "schema": {
                            "$ref": "#/definitions/backend_api_v1.LoginRequest"
                        }
                    }
                ],
                "responses": {
                    "200": {
                        "description": "OK",
                        "schema": {
                            "$ref": "#/definitions/backend_api_v1.LoginResponse"
                        }
                    }
                }
            }
        },
        "/register": {
            "post": {
                "description": "目前只支持邮箱登录",
                "consumes": [
                    "application/json"
                ],
                "produces": [
                    "application/json"
                ],
                "tags": [
                    "用户模块"
                ],
                "summary": "用户注册",
                "parameters": [
                    {
                        "description": "params",
                        "name": "request",
                        "in": "body",
                        "required": true,
                        "schema": {
                            "$ref": "#/definitions/backend_api_v1.RegisterRequest"
                        }
                    }
                ],
                "responses": {
                    "200": {
                        "description": "OK",
                        "schema": {
                            "$ref": "#/definitions/backend_api_v1.Response"
                        }
                    }
                }
            }
        },
        "/robot": {
            "get": {
                "security": [
                    {
                        "Bearer": []
                    }
                ],
                "consumes": [
                    "application/json"
                ],
                "produces": [
                    "application/json"
                ],
                "tags": [
                    "机器人模块"
                ],
                "summary": "获取机器人列表",
                "parameters": [
                    {
                        "type": "integer",
                        "description": "page",
                        "name": "page",
                        "in": "query"
                    },
                    {
                        "type": "integer",
                        "description": "size",
                        "name": "size",
                        "in": "query"
                    }
                ],
                "responses": {
                    "200": {
                        "description": "OK",
                        "schema": {
                            "$ref": "#/definitions/backend_api_v1.PageResponse-backend_api_v1_RobotResponseData"
                        }
                    }
                }
            },
            "post": {
                "security": [
                    {
                        "Bearer": []
                    }
                ],
                "consumes": [
                    "application/json"
                ],
                "produces": [
                    "application/json"
                ],
                "tags": [
                    "机器人模块"
                ],
                "summary": "创建机器人",
                "parameters": [
                    {
                        "description": "params",
                        "name": "request",
                        "in": "body",
                        "required": true,
                        "schema": {
                            "$ref": "#/definitions/backend_api_v1.RobotRequest"
                        }
                    }
                ],
                "responses": {
                    "200": {
                        "description": "OK",
                        "schema": {
                            "$ref": "#/definitions/backend_api_v1.RobotResponseData"
                        }
                    }
                }
            }
        },
        "/robot/{id}": {
            "get": {
                "security": [
                    {
                        "Bearer": []
                    }
                ],
                "consumes": [
                    "application/json"
                ],
                "produces": [
                    "application/json"
                ],
                "tags": [
                    "机器人模块"
                ],
                "summary": "获取机器人",
                "parameters": [
                    {
                        "type": "integer",
                        "description": "机器人ID",
                        "name": "id",
                        "in": "path",
                        "required": true
                    }
                ],
                "responses": {
                    "200": {
                        "description": "OK",
                        "schema": {
                            "$ref": "#/definitions/backend_api_v1.RobotResponseData"
                        }
                    }
                }
            },
            "put": {
                "security": [
                    {
                        "Bearer": []
                    }
                ],
                "consumes": [
                    "application/json"
                ],
                "produces": [
                    "application/json"
                ],
                "tags": [
                    "机器人模块"
                ],
                "summary": "更新机器人",
                "parameters": [
                    {
                        "type": "integer",
                        "description": "机器人ID",
                        "name": "id",
                        "in": "path",
                        "required": true
                    },
                    {
                        "description": "params",
                        "name": "request",
                        "in": "body",
                        "required": true,
                        "schema": {
                            "$ref": "#/definitions/backend_api_v1.RobotRequest"
                        }
                    }
                ],
                "responses": {
                    "200": {
                        "description": "OK",
                        "schema": {
                            "$ref": "#/definitions/backend_api_v1.RobotResponseData"
                        }
                    }
                }
            },
            "delete": {
                "security": [
                    {
                        "Bearer": []
                    }
                ],
                "consumes": [
                    "application/json"
                ],
                "produces": [
                    "application/json"
                ],
                "tags": [
                    "机器人模块"
                ],
                "summary": "删除机器人",
                "parameters": [
                    {
                        "type": "integer",
                        "description": "机器人ID",
                        "name": "id",
                        "in": "path",
                        "required": true
                    }
                ],
                "responses": {
                    "200": {
                        "description": "OK",
                        "schema": {
                            "$ref": "#/definitions/backend_api_v1.Response"
                        }
                    }
                }
            }
        },
        "/user": {
            "get": {
                "security": [
                    {
                        "Bearer": []
                    }
                ],
                "consumes": [
                    "application/json"
                ],
                "produces": [
                    "application/json"
                ],
                "tags": [
                    "用户模块"
                ],
                "summary": "获取用户信息",
                "responses": {
                    "200": {
                        "description": "OK",
                        "schema": {
                            "$ref": "#/definitions/backend_api_v1.GetProfileResponse"
                        }
                    }
                }
            },
            "put": {
                "security": [
                    {
                        "Bearer": []
                    }
                ],
                "consumes": [
                    "application/json"
                ],
                "produces": [
                    "application/json"
                ],
                "tags": [
                    "用户模块"
                ],
                "summary": "修改用户信息",
                "parameters": [
                    {
                        "description": "params",
                        "name": "request",
                        "in": "body",
                        "required": true,
                        "schema": {
                            "$ref": "#/definitions/backend_api_v1.UpdateProfileRequest"
                        }
                    }
                ],
                "responses": {
                    "200": {
                        "description": "OK",
                        "schema": {
                            "$ref": "#/definitions/backend_api_v1.Response"
                        }
                    }
                }
            }
        }
    },
    "definitions": {
        "backend_api_v1.GetProfileResponse": {
            "type": "object",
            "properties": {
                "code": {
                    "type": "integer"
                },
                "data": {
                    "$ref": "#/definitions/backend_api_v1.GetProfileResponseData"
                },
                "message": {
                    "type": "string"
                }
            }
        },
        "backend_api_v1.GetProfileResponseData": {
            "type": "object",
            "properties": {
                "nickname": {
                    "type": "string",
                    "example": "alan"
                },
                "userId": {
                    "type": "string"
                }
            }
        },
        "backend_api_v1.LoginRequest": {
            "type": "object",
            "required": [
                "email",
                "password"
            ],
            "properties": {
                "email": {
                    "type": "string",
                    "example": "1234@gmail.com"
                },
                "password": {
                    "type": "string",
                    "example": "123456"
                }
            }
        },
        "backend_api_v1.LoginResponse": {
            "type": "object",
            "properties": {
                "code": {
                    "type": "integer"
                },
                "data": {
                    "$ref": "#/definitions/backend_api_v1.LoginResponseData"
                },
                "message": {
                    "type": "string"
                }
            }
        },
        "backend_api_v1.LoginResponseData": {
            "type": "object",
            "properties": {
                "accessToken": {
                    "type": "string"
                }
            }
        },
        "backend_api_v1.PageResponse-backend_api_v1_RobotResponseData": {
            "type": "object",
            "properties": {
                "items": {
                    "type": "array",
                    "items": {
                        "$ref": "#/definitions/backend_api_v1.RobotResponseData"
                    }
                },
                "total": {
                    "type": "integer"
                }
            }
        },
        "backend_api_v1.RegisterRequest": {
            "type": "object",
            "required": [
                "email",
                "password"
            ],
            "properties": {
                "email": {
                    "type": "string",
                    "example": "1234@gmail.com"
                },
                "password": {
                    "type": "string",
                    "example": "123456"
                }
            }
        },
        "backend_api_v1.Response": {
            "type": "object",
            "properties": {
                "code": {
                    "type": "integer"
                },
                "data": {},
                "message": {
                    "type": "string"
                }
            }
        },
        "backend_api_v1.RobotRequest": {
            "type": "object",
            "required": [
                "name"
            ],
            "properties": {
                "callback": {
                    "type": "string"
                },
                "desc": {
                    "type": "string"
                },
                "enabled": {
                    "type": "boolean"
                },
                "name": {
                    "type": "string"
                },
                "options": {
                    "type": "string"
                },
                "owner": {
                    "type": "string"
                },
                "webhook": {
                    "type": "string"
                }
            }
        },
        "backend_api_v1.RobotResponseData": {
            "type": "object",
            "properties": {
                "callback": {
                    "type": "string",
                    "example": "https://callback.example.com"
                },
                "createdAt": {
                    "type": "string",
                    "example": "2006-01-02 15:04:05"
                },
                "desc": {
                    "type": "string",
                    "example": "it's a robot"
                },
                "enabled": {
                    "type": "boolean",
                    "example": true
                },
                "id": {
                    "type": "integer",
                    "example": 1
                },
                "name": {
                    "type": "string",
                    "example": "bot"
                },
                "options": {
                    "type": "string",
                    "example": "{\"key\": \"value\"}"
                },
                "owner": {
                    "type": "string",
                    "example": "Billy"
                },
                "robot_id": {
                    "type": "string",
                    "example": "454e7080-d105-4515-9c25-3e6fd9df176c"
                },
                "updatedAt": {
                    "type": "string",
                    "example": "2006-01-02 15:04:05"
                },
                "webhook": {
                    "type": "string",
                    "example": "https://webhook.example.com"
                }
            }
        },
        "backend_api_v1.UpdateProfileRequest": {
            "type": "object",
            "required": [
                "email"
            ],
            "properties": {
                "email": {
                    "type": "string",
                    "example": "1234@gmail.com"
                },
                "nickname": {
                    "type": "string",
                    "example": "alan"
                }
            }
        }
    },
    "securityDefinitions": {
        "Bearer": {
            "type": "apiKey",
            "name": "Authorization",
            "in": "header"
        }
    }
}